{
  "formatVersion": 1,
  "database": {
    "version": 2,
    "identityHash": "b2b0bb6ed631c29650eaad081a414e05",
    "entities": [
      {
        "tableName": "popular_artists",
        "createSql": "CREATE TABLE IF NOT EXISTS `${TABLE_NAME}` (`id` INTEGER NOT NULL, `name` TEXT, `popularity` REAL, `profilePath` TEXT, `knownFor` TEXT, PRIMARY KEY(`id`))",
        "fields": [
          {
            "fieldPath": "id",
            "columnName": "id",
            "affinity": "INTEGER",
            "notNull": true
          },
          {
            "fieldPath": "name",
            "columnName": "name",
            "affinity": "TEXT"
          },
          {
            "fieldPath": "popularity",
            "columnName": "popularity",
            "affinity": "REAL"
          },
          {
            "fieldPath": "profilePath",
            "columnName": "profilePath",
            "affinity": "TEXT"
          },
          {
            "fieldPath": "knownFor",
            "columnName": "knownFor",
            "affinity": "TEXT"
          }
        ],
        "primaryKey": {
          "autoGenerate": false,
          "columnNames": [
            "id"
          ]
        }
      },
      {
        "tableName": "popular_movies",
        "createSql": "CREATE TABLE IF NOT EXISTS `${TABLE_NAME}` (`id` INTEGER NOT NULL, `overview` TEXT, `posterPath` TEXT, `releaseDate` TEXT, `title` TEXT, PRIMARY KEY(`id`))",
        "fields": [
          {
            "fieldPath": "id",
            "columnName": "id",
            "affinity": "INTEGER",
            "notNull": true
          },
          {
            "fieldPath": "overview",
            "columnName": "overview",
            "affinity": "TEXT"
          },
          {
            "fieldPath": "posterPath",
            "columnName": "posterPath",
            "affinity": "TEXT"
          },
          {
            "fieldPath": "releaseDate",
            "columnName": "releaseDate",
            "affinity": "TEXT"
          },
          {
            "fieldPath": "title",
            "columnName": "title",
            "affinity": "TEXT"
          }
        ],
        "primaryKey": {
          "autoGenerate": false,
          "columnNames": [
            "id"
          ]
        }
      },
      {
        "tableName": "popular_tvShows",
        "createSql": "CREATE TABLE IF NOT EXISTS `${TABLE_NAME}` (`id` INTEGER NOT NULL, `firstAirDate` TEXT, `name` TEXT, `overview` TEXT, `posterPath` TEXT, PRIMARY KEY(`id`))",
        "fields": [
          {
            "fieldPath": "id",
            "columnName": "id",
            "affinity": "INTEGER",
            "notNull": true
          },
          {
            "fieldPath": "firstAirDate",
            "columnName": "firstAirDate",
            "affinity": "TEXT"
          },
          {
            "fieldPath": "name",
            "columnName": "name",
            "affinity": "TEXT"
          },
          {
            "fieldPath": "overview",
            "columnName": "overview",
            "affinity": "TEXT"
          },
          {
            "fieldPath": "posterPath",
            "columnName": "posterPath",
            "affinity": "TEXT"
          }
        ],
        "primaryKey": {
          "autoGenerate": false,
          "columnNames": [
            "id"
          ]
        }
      }
    ],
    "setupQueries": [
      "CREATE TABLE IF NOT EXISTS room_master_table (id INTEGER PRIMARY KEY,identity_hash TEXT)",
      "INSERT OR REPLACE INTO room_master_table (id,identity_hash) VALUES(42, 'b2b0bb6ed631c29650eaad081a414e05')"
    ]
  }
}